vrecord/__init__.py
vrecord/main.py
vrecord/recorder.py
vrecord-1.0.4.dist-info/LICENSE
vrecord-1.0.4.dist-info/METADATA
vrecord-1.0.4.dist-info/WHEEL
vrecord-1.0.4.dist-info/entry_points.txt
vrecord-1.0.4.dist-info/top_level.txt
vrecord-1.0.4.dist-info/RECORD
